{
"display":
{
"icon":
{
"id":"minecraft:flow_armor_trim_smithing_template"
},


"title":"Flow Plating - Armor                              ",
"description":"When wearing a full set of armor trimmed with this Pattern gain the ability to increase Haste when mining or attacking",
"frame":"goal",
"show_toast":true,
"announce_to_chat":true,
"hidden":true
},

"parent":"runechant:physical_crafting/smithing_template_spire",

"criteria":
{
"requirement":
{


"trigger":"minecraft:impossible"
}
}
}
