{
"display":
{
"icon":
{
"id":"minecraft:bone_meal",
"components":{"minecraft:custom_model_data":19974}
},


"title":"Grinding Plants into Paste                              ",
"description":"Grind some plants into paste using the Grinding Station [Required: 1x Any Plant | Drop Craft With: Grinding Station]",
"frame":"task",
"show_toast":true,
"announce_to_chat":true,
"hidden":false
},

"parent":"runechant:alchemy/grinding_station",

"criteria":
{
"requirement":
{


"trigger":"minecraft:impossible"
}
}
}
